ctypestoast/LICENSE
ctypestoast/README.md
ctypestoast/__init__.py
ctypestoast/requirements.txt
ctypestoast/thirdparty.json
ctypestoast-0.10.dist-info/LICENSE.rst
ctypestoast-0.10.dist-info/METADATA
ctypestoast-0.10.dist-info/WHEEL
ctypestoast-0.10.dist-info/top_level.txt
ctypestoast-0.10.dist-info/RECORD
