Metadata-Version: 2.1
Name: ctypestoast
Version: 0.10
Summary: Toast notification for Windows - ctypes only - no dependency
Home-page: https://github.com/hansalemaos/ctypestoast
Author: Johannes Fischer
Author-email: aulasparticularesdealemaosp@gmail.com
License: MIT
Keywords: ctypes,toast
Classifier: Development Status :: 4 - Beta
Classifier: Programming Language :: Python :: 3 :: Only
Classifier: Programming Language :: Python :: 3.10
Classifier: Topic :: Software Development :: Libraries :: Python Modules
Classifier: Topic :: Utilities
License-File: LICENSE.rst
